kivy_garden/zbarcam/__init__.py
kivy_garden/zbarcam/utils.py
kivy_garden/zbarcam/version.py
kivy_garden/zbarcam/zbarcam.kv
kivy_garden/zbarcam/zbarcam.py
zbarcam-2020.524.dist-info/LICENSE
zbarcam-2020.524.dist-info/METADATA
zbarcam-2020.524.dist-info/WHEEL
zbarcam-2020.524.dist-info/top_level.txt
zbarcam-2020.524.dist-info/RECORD
