Metadata-Version: 2.1
Name: zbarcam
Version: 2020.524
Summary: Real time Barcode and QR Code scanner Edit
Home-page: https://github.com/kivy-garden/zbarcam
Author: Andre Miras
License: UNKNOWN
Platform: UNKNOWN
